Metadata-Version: 2.1
Name: solidAPI
Version: 0.1.8.1
Summary: A Library for solidAPI
Home-page: https://github.com/DoellBarr
Author: Shohih Abdul
Author-email: shohih242@gmail.com
License: MIT
Platform: UNKNOWN
Classifier: Development Status :: 5 - Production/Stable
Classifier: Intended Audience :: Developers
Classifier: License :: OSI Approved :: MIT License
Classifier: Programming Language :: Python :: 3
Classifier: Programming Language :: Python :: 3.7
Classifier: Programming Language :: Python :: 3.8
Classifier: Programming Language :: Python :: 3.9
